{"failedItems":[],"newItems":[],"deletedItems":[],"passedItems":["shared-app-image--primary.png","shared-app-link--active.png","shared-app-link--bg-primary.png","shared-app-link--brand.png","shared-app-link--outline.png","shared-app-link--regular.png"],"expectedItems":["shared-app-image--primary.png","shared-app-link--active.png","shared-app-link--bg-primary.png","shared-app-link--brand.png","shared-app-link--outline.png","shared-app-link--regular.png"],"actualItems":["shared-app-image--primary.png","shared-app-link--active.png","shared-app-link--bg-primary.png","shared-app-link--brand.png","shared-app-link--outline.png","shared-app-link--regular.png"],"diffItems":[],"actualDir":"./.lostpixel\\current","expectedDir":"./.lostpixel\\baseline","diffDir":"./.lostpixel\\difference"}